rivia_cognito_authorizer/__init__.py
rivia_cognito_authorizer/_version.py
rivia_cognito_authorizer/main.py
rivia_cognito_authorizer-1.1.0.dist-info/licenses/LICENSE
rivia_cognito_authorizer-1.1.0.dist-info/METADATA
rivia_cognito_authorizer-1.1.0.dist-info/WHEEL
rivia_cognito_authorizer-1.1.0.dist-info/top_level.txt
rivia_cognito_authorizer-1.1.0.dist-info/RECORD
