Metadata-Version: 2.4
Name: rivia-cognito-authorizer
Version: 1.1.0
Summary: Cognito authorizer for fastapi based projects
Author-email: Rivia Backend Team <backend@riviadev.com.br>
License: MIT License
Keywords: elasticsearch,cloud,query-builder,python
Classifier: Development Status :: 3 - Alpha
Classifier: Programming Language :: Python :: 3.8
Classifier: License :: OSI Approved :: MIT License
Classifier: Operating System :: OS Independent
Requires-Python: >=3.11
License-File: LICENSE
Requires-Dist: boto3>=1.36.17
Requires-Dist: fastapi>=0.115.8
Requires-Dist: pyjwt>=1.3.1
Requires-Dist: requests>=2.32.3
Requires-Dist: cryptography>=44.0.0
Dynamic: license-file
